MANIFEST.in
requirements.txt
setup.py
src/workspace.py
src/djworkspace/__init__.py
src/djworkspace/admin.py
src/djworkspace/apps.py
src/djworkspace/cache.py
src/djworkspace/models.py
src/djworkspace/store.py
src/djworkspace/views.py
src/djworkspace/migrations/0001_initial.py
src/djworkspace/migrations/0002_auto_20171109_0707.py
src/djworkspace/migrations/0003_auto_20171109_0723.py
src/djworkspace/migrations/__init__.py
src/djworkspace/tests/__init__.py
src/djworkspace/tests/test_cache.py
src/djworkspace/tests/test_django_workspace.py
src/fake/__init__.py
src/fake/admin.py
src/fake/apps.py
src/fake/models.py
src/fake/tests.py
src/fake/views.py
src/fake/migrations/0001_initial.py
src/fake/migrations/__init__.py
src/livingbio_workspace.egg-info/PKG-INFO
src/livingbio_workspace.egg-info/SOURCES.txt
src/livingbio_workspace.egg-info/dependency_links.txt
src/livingbio_workspace.egg-info/not-zip-safe
src/livingbio_workspace.egg-info/requires.txt
src/livingbio_workspace.egg-info/top_level.txt
src/tests/__init__.py
src/tests/test_workspace.py
src/website/__init__.py
src/website/settings.py
src/website/urls.py
src/website/wsgi.py